{"rootTag":null,"format":"xml","ignoreSurroundingSpaces":null,"ignoreNamespace":null,"path":"dbfs:/prophecy_data/web/bronze/sitemap/","declaration":null,"excludeAttribute":null,"valueTag":null,"writeMode":null,"description":"Website sitemap data that outlines the structure of web pages, including their update frequency and importance, aiding in search engine optimization and content management.","compression":null,"nullValue":null,"timestampFormat":null,"partitionColumns":null,"schema":{"type":"struct","fields":[{"name":"changefreq","type":"string","nullable":true,"metadata":{"description":"Frequency at which the content of the URL is expected to change; Indicates how often the page is updated.","mappings":[],"tags":[]}},{"name":"loc","type":"string","nullable":true,"metadata":{"description":"The URL location of the resource; Represents the web address of the sitemap entry.","mappings":[],"tags":[]}},{"name":"priority","type":"double","nullable":true,"metadata":{"description":"Indicates the importance of the URL in the sitemap; A higher value signifies a higher priority for search engines.","mappings":[],"tags":[]}}]},"additionalProperties":{"copilot":{"datasetDescriptionStatus":"fromCopilotWithInterim"}},"componentInfo":{"gemId":"gitUri=http://gitserver:3000/DxEheDCJ_team_5751/DxEheDCJ_project_12654.git&subPath=&tag=0.2.28&projectSubscriptionProjectId=12654&path=gems/xml","projectName":"ProphecySparkBasicsPython"},"dateFormat":null,"mode":null,"rowTag":"url","attributePrefix":null,"datasetType":"File","useSchema":true}